{
  "item": [
    {
      "id": "fc2459a6-d7f0-4ecf-91c1-2039a522ccfb",
      "name": "Import Jobs",
      "description": {
        "content": "Create and manage data import jobs",
        "type": "text/plain"
      },
      "item": [
        {
          "id": "f91954a1-4d24-465e-ab4d-6ccc38f027f7",
          "name": "Demandbase List import jobs",
          "request": {
            "name": "Demandbase List import jobs",
            "description": {
              "content": "Retrieve a list of data import jobs with their current status.",
              "type": "text/plain"
            },
            "url": {
              "path": [
                "import",
                "v1",
                "jobs"
              ],
              "host": [
                "{{baseUrl}}"
              ],
              "query": [
                {
                  "disabled": false,
                  "key": "status",
                  "value": "<string>",
                  "description": "Filter by job status"
                },
                {
                  "disabled": false,
                  "key": "limit",
                  "value": "25"
                },
                {
                  "disabled": false,
                  "key": "offset",
                  "value": "0"
                }
              ],
              "variable": []
            },
            "header": [
              {
                "key": "Accept",
                "value": "application/json"
              }
            ],
            "method": "GET",
            "auth": null
          },
          "response": [
            {
              "id": "796fa9d1-57c8-4c83-891f-5a341aa7493f",
              "name": "List of import jobs",
              "originalRequest": {
                "url": {
                  "path": [
                    "import",
                    "v1",
                    "jobs"
                  ],
                  "host": [
                    "{{baseUrl}}"
                  ],
                  "query": [
                    {
                      "key": "status",
                      "value": "<string>"
                    },
                    {
                      "key": "limit",
                      "value": "25"
                    },
                    {
                      "key": "offset",
                      "value": "0"
                    }
                  ],
                  "variable": []
                },
                "header": [
                  {
                    "description": {
                      "content": "Added as a part of security scheme: bearer",
                      "type": "text/plain"
                    },
                    "key": "Authorization",
                    "value": "Bearer <token>"
                  },
                  {
                    "key": "Accept",
                    "value": "application/json"
                  }
                ],
                "method": "GET",
                "body": {}
              },
              "status": "OK",
              "code": 200,
              "header": [
                {
                  "key": "Content-Type",
                  "value": "application/json"
                }
              ],
              "body": "{\n  \"jobs\": [\n    {\n      \"id\": \"string\",\n      \"entity_type\": \"accounts\",\n      \"operation\": \"upsert\",\n      \"status\": \"processing\",\n      \"total_rows\": 1893,\n      \"processed_rows\": 6004,\n      \"success_count\": 9014,\n      \"error_count\": 2327,\n      \"file_name\": \"string\",\n      \"file_size_bytes\": 6335,\n      \"created_at\": \"2016-06-30T19:16:38.690Z\",\n      \"started_at\": \"2004-06-10T12:21:40.493Z\",\n      \"completed_at\": \"1952-08-18T18:51:43.366Z\",\n      \"error_message\": \"string\"\n    },\n    {\n      \"id\": \"string\",\n      \"entity_type\": \"opportunities\",\n      \"operation\": \"insert\",\n      \"status\": \"failed\",\n      \"total_rows\": 7112,\n      \"processed_rows\": 8965,\n      \"success_count\": 1839,\n      \"error_count\": 3814,\n      \"file_name\": \"string\",\n      \"file_size_bytes\": 2410,\n      \"created_at\": \"2026-03-15T20:44:05.329Z\",\n      \"started_at\": \"1951-10-04T11:07:27.077Z\",\n      \"completed_at\": \"2025-11-07T07:09:40.352Z\",\n      \"error_message\": \"string\"\n    }\n  ],\n  \"total\": 3516\n}",
              "cookie": [],
              "_postman_previewlanguage": "json"
            },
            {
              "id": "f5c65cfb-8326-4741-80f7-10733e1fedc5",
              "name": "Unauthorized",
              "originalRequest": {
                "url": {
                  "path": [
                    "import",
                    "v1",
                    "jobs"
                  ],
                  "host": [
                    "{{baseUrl}}"
                  ],
                  "query": [
                    {
                      "key": "status",
                      "value": "<string>"
                    },
                    {
                      "key": "limit",
                      "value": "25"
                    },
                    {
                      "key": "offset",
                      "value": "0"
                    }
                  ],
                  "variable": []
                },
                "header": [
                  {
                    "description": {
                      "content": "Added as a part of security scheme: bearer",
                      "type": "text/plain"
                    },
                    "key": "Authorization",
                    "value": "Bearer <token>"
                  }
                ],
                "method": "GET",
                "body": {}
              },
              "status": "Unauthorized",
              "code": 401,
              "header": [
                {
                  "key": "Content-Type",
                  "value": "text/plain"
                }
              ],
              "body": "",
              "cookie": [],
              "_postman_previewlanguage": "text"
            }
          ],
          "event": [],
          "protocolProfileBehavior": {
            "disableBodyPruning": true
          }
        },
        {
          "id": "163075fc-36c3-41a0-ae3b-4bde23b3baad",
          "name": "Demandbase Create an import job",
          "request": {
            "name": "Demandbase Create an import job",
            "description": {
              "content": "Create a new asynchronous data import job. Specify the entity type, operation mode (insert, update, or upsert), and field mappings. Upload the CSV data file after creating the job.",
              "type": "text/plain"
            },
            "url": {
              "path": [
                "import",
                "v1",
                "jobs"
              ],
              "host": [
                "{{baseUrl}}"
              ],
              "query": [],
              "variable": []
            },
            "header": [
              {
                "key": "Content-Type",
                "value": "application/json"
              },
              {
                "key": "Accept",
                "value": "application/json"
              }
            ],
            "method": "POST",
            "auth": null,
            "body": {
              "mode": "raw",
              "raw": "{\n  \"entity_type\": \"<string>\",\n  \"operation\": \"<string>\",\n  \"match_key\": \"<string>\",\n  \"field_mappings\": [\n    {\n      \"csv_column\": \"<string>\",\n      \"demandbase_field\": \"<string>\"\n    },\n    {\n      \"csv_column\": \"<string>\",\n      \"demandbase_field\": \"<string>\"\n    }\n  ]\n}",
              "options": {
                "raw": {
                  "language": "json"
                }
              }
            }
          },
          "response": [
            {
              "id": "967419b1-a596-4c6a-8e22-d8a123bfc93c",
              "name": "Import job created",
              "originalRequest": {
                "url": {
                  "path": [
                    "import",
                    "v1",
                    "jobs"
                  ],
                  "host": [
                    "{{baseUrl}}"
                  ],
                  "query": [],
                  "variable": []
                },
                "header": [
                  {
                    "description": {
                      "content": "Added as a part of security scheme: bearer",
                      "type": "text/plain"
                    },
                    "key": "Authorization",
                    "value": "Bearer <token>"
                  },
                  {
                    "key": "Accept",
                    "value": "application/json"
                  }
                ],
                "method": "POST",
                "body": {
                  "mode": "raw",
                  "raw": "{\n  \"entity_type\": \"<string>\",\n  \"operation\": \"<string>\",\n  \"match_key\": \"<string>\",\n  \"field_mappings\": [\n    {\n      \"csv_column\": \"<string>\",\n      \"demandbase_field\": \"<string>\"\n    },\n    {\n      \"csv_column\": \"<string>\",\n      \"demandbase_field\": \"<string>\"\n    }\n  ]\n}",
                  "options": {
                    "raw": {
                      "language": "json"
                    }
                  }
                }
              },
              "status": "Accepted",
              "code": 202,
              "header": [
                {
                  "key": "Content-Type",
                  "value": "application/json"
                }
              ],
              "body": "{\n  \"id\": \"string\",\n  \"entity_type\": \"people\",\n  \"operation\": \"upsert\",\n  \"status\": \"failed\",\n  \"total_rows\": 1407,\n  \"processed_rows\": 8801,\n  \"success_count\": 2038,\n  \"error_count\": 7944,\n  \"file_name\": \"string\",\n  \"file_size_bytes\": 2317,\n  \"created_at\": \"1962-04-02T00:35:19.543Z\",\n  \"started_at\": \"1958-12-01T04:03:40.061Z\",\n  \"completed_at\": \"1960-02-06T06:03:52.607Z\",\n  \"error_message\": \"string\"\n}",
              "cookie": [],
              "_postman_previewlanguage": "json"
            },
            {
              "id": "470c4c90-4465-41d8-ad17-a82f6cbc3628",
              "name": "Invalid request",
              "originalRequest": {
                "url": {
                  "path": [
                    "import",
                    "v1",
                    "jobs"
                  ],
                  "host": [
                    "{{baseUrl}}"
                  ],
                  "query": [],
                  "variable": []
                },
                "header": [
                  {
                    "description": {
                      "content": "Added as a part of security scheme: bearer",
                      "type": "text/plain"
                    },
                    "key": "Authorization",
                    "value": "Bearer <token>"
                  }
                ],
                "method": "POST",
                "body": {
                  "mode": "raw",
                  "raw": "{\n  \"entity_type\": \"<string>\",\n  \"operation\": \"<string>\",\n  \"match_key\": \"<string>\",\n  \"field_mappings\": [\n    {\n      \"csv_column\": \"<string>\",\n      \"demandbase_field\": \"<string>\"\n    },\n    {\n      \"csv_column\": \"<string>\",\n      \"demandbase_field\": \"<string>\"\n    }\n  ]\n}",
                  "options": {
                    "raw": {
                      "language": "json"
                    }
                  }
                }
              },
              "status": "Bad Request",
              "code": 400,
              "header": [
                {
                  "key": "Content-Type",
                  "value": "text/plain"
                }
              ],
              "body": "",
              "cookie": [],
              "_postman_previewlanguage": "text"
            },
            {
              "id": "76c42109-f34c-4cb3-978f-7969292cfca3",
              "name": "Unauthorized",
              "originalRequest": {
                "url": {
                  "path": [
                    "import",
                    "v1",
                    "jobs"
                  ],
                  "host": [
                    "{{baseUrl}}"
                  ],
                  "query": [],
                  "variable": []
                },
                "header": [
                  {
                    "description": {
                      "content": "Added as a part of security scheme: bearer",
                      "type": "text/plain"
                    },
                    "key": "Authorization",
                    "value": "Bearer <token>"
                  }
                ],
                "method": "POST",
                "body": {
                  "mode": "raw",
                  "raw": "{\n  \"entity_type\": \"<string>\",\n  \"operation\": \"<string>\",\n  \"match_key\": \"<string>\",\n  \"field_mappings\": [\n    {\n      \"csv_column\": \"<string>\",\n      \"demandbase_field\": \"<string>\"\n    },\n    {\n      \"csv_column\": \"<string>\",\n      \"demandbase_field\": \"<string>\"\n    }\n  ]\n}",
                  "options": {
                    "raw": {
                      "language": "json"
                    }
                  }
                }
              },
              "status": "Unauthorized",
              "code": 401,
              "header": [
                {
                  "key": "Content-Type",
                  "value": "text/plain"
                }
              ],
              "body": "",
              "cookie": [],
              "_postman_previewlanguage": "text"
            }
          ],
          "event": [],
          "protocolProfileBehavior": {
            "disableBodyPruning": true
          }
        },
        {
          "id": "4ea2f454-1294-488b-ac36-89615dde6d34",
          "name": "Demandbase Get import job status",
          "request": {
            "name": "Demandbase Get import job status",
            "description": {
              "content": "Retrieve the current status and details of a specific import job, including processing progress and error summary.",
              "type": "text/plain"
            },
            "url": {
              "path": [
                "import",
                "v1",
                "jobs",
                ":jobId"
              ],
              "host": [
                "{{baseUrl}}"
              ],
              "query": [],
              "variable": [
                {
                  "disabled": false,
                  "type": "any",
                  "value": "<string>",
                  "key": "jobId",
                  "description": "(Required) Import job unique identifier"
                }
              ]
            },
            "header": [
              {
                "key": "Accept",
                "value": "application/json"
              }
            ],
            "method": "GET",
            "auth": null
          },
          "response": [
            {
              "id": "8f910b41-b138-4ef9-85a2-f8e77743e90c",
              "name": "Import job details",
              "originalRequest": {
                "url": {
                  "path": [
                    "import",
                    "v1",
                    "jobs",
                    ":jobId"
                  ],
                  "host": [
                    "{{baseUrl}}"
                  ],
                  "query": [],
                  "variable": [
                    {
                      "disabled": false,
                      "type": "any",
                      "value": "<string>",
                      "key": "jobId",
                      "description": "(Required) Import job unique identifier"
                    }
                  ]
                },
                "header": [
                  {
                    "description": {
                      "content": "Added as a part of security scheme: bearer",
                      "type": "text/plain"
                    },
                    "key": "Authorization",
                    "value": "Bearer <token>"
                  },
                  {
                    "key": "Accept",
                    "value": "application/json"
                  }
                ],
                "method": "GET",
                "body": {}
              },
              "status": "OK",
              "code": 200,
              "header": [
                {
                  "key": "Content-Type",
                  "value": "application/json"
                }
              ],
              "body": "{\n  \"id\": \"string\",\n  \"entity_type\": \"people\",\n  \"operation\": \"upsert\",\n  \"status\": \"failed\",\n  \"total_rows\": 1407,\n  \"processed_rows\": 8801,\n  \"success_count\": 2038,\n  \"error_count\": 7944,\n  \"file_name\": \"string\",\n  \"file_size_bytes\": 2317,\n  \"created_at\": \"1962-04-02T00:35:19.543Z\",\n  \"started_at\": \"1958-12-01T04:03:40.061Z\",\n  \"completed_at\": \"1960-02-06T06:03:52.607Z\",\n  \"error_message\": \"string\"\n}",
              "cookie": [],
              "_postman_previewlanguage": "json"
            },
            {
              "id": "9f47f1d8-cead-46f5-a3c5-ef998e512d06",
              "name": "Unauthorized",
              "originalRequest": {
                "url": {
                  "path": [
                    "import",
                    "v1",
                    "jobs",
                    ":jobId"
                  ],
                  "host": [
                    "{{baseUrl}}"
                  ],
                  "query": [],
                  "variable": [
                    {
                      "disabled": false,
                      "type": "any",
                      "value": "<string>",
                      "key": "jobId",
                      "description": "(Required) Import job unique identifier"
                    }
                  ]
                },
                "header": [
                  {
                    "description": {
                      "content": "Added as a part of security scheme: bearer",
                      "type": "text/plain"
                    },
                    "key": "Authorization",
                    "value": "Bearer <token>"
                  }
                ],
                "method": "GET",
                "body": {}
              },
              "status": "Unauthorized",
              "code": 401,
              "header": [
                {
                  "key": "Content-Type",
                  "value": "text/plain"
                }
              ],
              "body": "",
              "cookie": [],
              "_postman_previewlanguage": "text"
            },
            {
              "id": "8320cb34-0231-4dcb-b6d4-13f07e6c4e23",
              "name": "Import job not found",
              "originalRequest": {
                "url": {
                  "path": [
                    "import",
                    "v1",
                    "jobs",
                    ":jobId"
                  ],
                  "host": [
                    "{{baseUrl}}"
                  ],
                  "query": [],
                  "variable": [
                    {
                      "disabled": false,
                      "type": "any",
                      "value": "<string>",
                      "key": "jobId",
                      "description": "(Required) Import job unique identifier"
                    }
                  ]
                },
                "header": [
                  {
                    "description": {
                      "content": "Added as a part of security scheme: bearer",
                      "type": "text/plain"
                    },
                    "key": "Authorization",
                    "value": "Bearer <token>"
                  }
                ],
                "method": "GET",
                "body": {}
              },
              "status": "Not Found",
              "code": 404,
              "header": [
                {
                  "key": "Content-Type",
                  "value": "text/plain"
                }
              ],
              "body": "",
              "cookie": [],
              "_postman_previewlanguage": "text"
            }
          ],
          "event": [],
          "protocolProfileBehavior": {
            "disableBodyPruning": true
          }
        },
        {
          "id": "86e3f91f-c4aa-4316-ab99-a6486a157c1e",
          "name": "Demandbase Cancel an import job",
          "request": {
            "name": "Demandbase Cancel an import job",
            "description": {
              "content": "Cancel a pending or validating import job.",
              "type": "text/plain"
            },
            "url": {
              "path": [
                "import",
                "v1",
                "jobs",
                ":jobId"
              ],
              "host": [
                "{{baseUrl}}"
              ],
              "query": [],
              "variable": [
                {
                  "disabled": false,
                  "type": "any",
                  "value": "<string>",
                  "key": "jobId",
                  "description": "(Required) Import job unique identifier"
                }
              ]
            },
            "method": "DELETE",
            "auth": null
          },
          "response": [
            {
              "id": "61b1f354-8525-4c90-9c8d-353b9618286b",
              "name": "Import job cancelled",
              "originalRequest": {
                "url": {
                  "path": [
                    "import",
                    "v1",
                    "jobs",
                    ":jobId"
                  ],
                  "host": [
                    "{{baseUrl}}"
                  ],
                  "query": [],
                  "variable": [
                    {
                      "disabled": false,
                      "type": "any",
                      "value": "<string>",
                      "key": "jobId",
                      "description": "(Required) Import job unique identifier"
                    }
                  ]
                },
                "header": [
                  {
                    "description": {
                      "content": "Added as a part of security scheme: bearer",
                      "type": "text/plain"
                    },
                    "key": "Authorization",
                    "value": "Bearer <token>"
                  }
                ],
                "method": "DELETE",
                "body": {}
              },
              "status": "OK",
              "code": 200,
              "header": [
                {
                  "key": "Content-Type",
                  "value": "text/plain"
                }
              ],
              "body": "",
              "cookie": [],
              "_postman_previewlanguage": "text"
            },
            {
              "id": "0734ac51-c4cf-4774-9bbb-3771993bf31a",
              "name": "Unauthorized",
              "originalRequest": {
                "url": {
                  "path": [
                    "import",
                    "v1",
                    "jobs",
                    ":jobId"
                  ],
                  "host": [
                    "{{baseUrl}}"
                  ],
                  "query": [],
                  "variable": [
                    {
                      "disabled": false,
                      "type": "any",
                      "value": "<string>",
                      "key": "jobId",
                      "description": "(Required) Import job unique identifier"
                    }
                  ]
                },
                "header": [
                  {
                    "description": {
                      "content": "Added as a part of security scheme: bearer",
                      "type": "text/plain"
                    },
                    "key": "Authorization",
                    "value": "Bearer <token>"
                  }
                ],
                "method": "DELETE",
                "body": {}
              },
              "status": "Unauthorized",
              "code": 401,
              "header": [
                {
                  "key": "Content-Type",
                  "value": "text/plain"
                }
              ],
              "body": "",
              "cookie": [],
              "_postman_previewlanguage": "text"
            },
            {
              "id": "031eb42e-a0bb-4fd2-8d87-17ea6339dab0",
              "name": "Import job not found",
              "originalRequest": {
                "url": {
                  "path": [
                    "import",
                    "v1",
                    "jobs",
                    ":jobId"
                  ],
                  "host": [
                    "{{baseUrl}}"
                  ],
                  "query": [],
                  "variable": [
                    {
                      "disabled": false,
                      "type": "any",
                      "value": "<string>",
                      "key": "jobId",
                      "description": "(Required) Import job unique identifier"
                    }
                  ]
                },
                "header": [
                  {
                    "description": {
                      "content": "Added as a part of security scheme: bearer",
                      "type": "text/plain"
                    },
                    "key": "Authorization",
                    "value": "Bearer <token>"
                  }
                ],
                "method": "DELETE",
                "body": {}
              },
              "status": "Not Found",
              "code": 404,
              "header": [
                {
                  "key": "Content-Type",
                  "value": "text/plain"
                }
              ],
              "body": "",
              "cookie": [],
              "_postman_previewlanguage": "text"
            },
            {
              "id": "85583ef2-bc7e-43ac-83d4-b3d71609380e",
              "name": "Job cannot be cancelled",
              "originalRequest": {
                "url": {
                  "path": [
                    "import",
                    "v1",
                    "jobs",
                    ":jobId"
                  ],
                  "host": [
                    "{{baseUrl}}"
                  ],
                  "query": [],
                  "variable": [
                    {
                      "disabled": false,
                      "type": "any",
                      "value": "<string>",
                      "key": "jobId",
                      "description": "(Required) Import job unique identifier"
                    }
                  ]
                },
                "header": [
                  {
                    "description": {
                      "content": "Added as a part of security scheme: bearer",
                      "type": "text/plain"
                    },
                    "key": "Authorization",
                    "value": "Bearer <token>"
                  }
                ],
                "method": "DELETE",
                "body": {}
              },
              "status": "Conflict",
              "code": 409,
              "header": [
                {
                  "key": "Content-Type",
                  "value": "text/plain"
                }
              ],
              "body": "",
              "cookie": [],
              "_postman_previewlanguage": "text"
            }
          ],
          "event": [],
          "protocolProfileBehavior": {
            "disableBodyPruning": true
          }
        },
        {
          "id": "79631510-72f2-4901-8d65-22e88a68a942",
          "name": "Demandbase Get import errors",
          "request": {
            "name": "Demandbase Get import errors",
            "description": {
              "content": "Retrieve detailed error information for rows that failed during import.",
              "type": "text/plain"
            },
            "url": {
              "path": [
                "import",
                "v1",
                "jobs",
                ":jobId",
                "errors"
              ],
              "host": [
                "{{baseUrl}}"
              ],
              "query": [
                {
                  "disabled": false,
                  "key": "limit",
                  "value": "100"
                },
                {
                  "disabled": false,
                  "key": "offset",
                  "value": "0"
                }
              ],
              "variable": [
                {
                  "disabled": false,
                  "type": "any",
                  "value": "<string>",
                  "key": "jobId",
                  "description": "(Required) Import job unique identifier"
                }
              ]
            },
            "header": [
              {
                "key": "Accept",
                "value": "application/json"
              }
            ],
            "method": "GET",
            "auth": null
          },
          "response": [
            {
              "id": "e6513c2b-1395-4974-af6e-d114d58d96df",
              "name": "Import errors",
              "originalRequest": {
                "url": {
                  "path": [
                    "import",
                    "v1",
                    "jobs",
                    ":jobId",
                    "errors"
                  ],
                  "host": [
                    "{{baseUrl}}"
                  ],
                  "query": [
                    {
                      "key": "limit",
                      "value": "100"
                    },
                    {
                      "key": "offset",
                      "value": "0"
                    }
                  ],
                  "variable": [
                    {
                      "disabled": false,
                      "type": "any",
                      "value": "<string>",
                      "key": "jobId",
                      "description": "(Required) Import job unique identifier"
                    }
                  ]
                },
                "header": [
                  {
                    "description": {
                      "content": "Added as a part of security scheme: bearer",
                      "type": "text/plain"
                    },
                    "key": "Authorization",
                    "value": "Bearer <token>"
                  },
                  {
                    "key": "Accept",
                    "value": "application/json"
                  }
                ],
                "method": "GET",
                "body": {}
              },
              "status": "OK",
              "code": 200,
              "header": [
                {
                  "key": "Content-Type",
                  "value": "application/json"
                }
              ],
              "body": "{\n  \"errors\": [\n    {\n      \"row_number\": 6465,\n      \"field\": \"string\",\n      \"value\": \"string\",\n      \"error_type\": \"string\",\n      \"message\": \"string\"\n    },\n    {\n      \"row_number\": 4768,\n      \"field\": \"string\",\n      \"value\": \"string\",\n      \"error_type\": \"string\",\n      \"message\": \"string\"\n    }\n  ],\n  \"total\": 754\n}",
              "cookie": [],
              "_postman_previewlanguage": "json"
            },
            {
              "id": "e26b4ce5-3951-47e7-9bb3-790e443bc716",
              "name": "Unauthorized",
              "originalRequest": {
                "url": {
                  "path": [
                    "import",
                    "v1",
                    "jobs",
                    ":jobId",
                    "errors"
                  ],
                  "host": [
                    "{{baseUrl}}"
                  ],
                  "query": [
                    {
                      "key": "limit",
                      "value": "100"
                    },
                    {
                      "key": "offset",
                      "value": "0"
                    }
                  ],
                  "variable": [
                    {
                      "disabled": false,
                      "type": "any",
                      "value": "<string>",
                      "key": "jobId",
                      "description": "(Required) Import job unique identifier"
                    }
                  ]
                },
                "header": [
                  {
                    "description": {
                      "content": "Added as a part of security scheme: bearer",
                      "type": "text/plain"
                    },
                    "key": "Authorization",
                    "value": "Bearer <token>"
                  }
                ],
                "method": "GET",
                "body": {}
              },
              "status": "Unauthorized",
              "code": 401,
              "header": [
                {
                  "key": "Content-Type",
                  "value": "text/plain"
                }
              ],
              "body": "",
              "cookie": [],
              "_postman_previewlanguage": "text"
            },
            {
              "id": "0251863f-7f26-492b-951a-a8f682947a64",
              "name": "Import job not found",
              "originalRequest": {
                "url": {
                  "path": [
                    "import",
                    "v1",
                    "jobs",
                    ":jobId",
                    "errors"
                  ],
                  "host": [
                    "{{baseUrl}}"
                  ],
                  "query": [
                    {
                      "key": "limit",
                      "value": "100"
                    },
                    {
                      "key": "offset",
                      "value": "0"
                    }
                  ],
                  "variable": [
                    {
                      "disabled": false,
                      "type": "any",
                      "value": "<string>",
                      "key": "jobId",
                      "description": "(Required) Import job unique identifier"
                    }
                  ]
                },
                "header": [
                  {
                    "description": {
                      "content": "Added as a part of security scheme: bearer",
                      "type": "text/plain"
                    },
                    "key": "Authorization",
                    "value": "Bearer <token>"
                  }
                ],
                "method": "GET",
                "body": {}
              },
              "status": "Not Found",
              "code": 404,
              "header": [
                {
                  "key": "Content-Type",
                  "value": "text/plain"
                }
              ],
              "body": "",
              "cookie": [],
              "_postman_previewlanguage": "text"
            }
          ],
          "event": [],
          "protocolProfileBehavior": {
            "disableBodyPruning": true
          }
        }
      ],
      "event": []
    },
    {
      "id": "3eb6353b-2560-4aa8-9391-66d88ea06017",
      "name": "Mappings",
      "description": {
        "content": "Field mapping configuration",
        "type": "text/plain"
      },
      "item": [
        {
          "id": "f51b9782-d4e5-4f8a-8210-bfa4db5f7702",
          "name": "Demandbase List field mappings",
          "request": {
            "name": "Demandbase List field mappings",
            "description": {
              "content": "Retrieve available field mappings for each entity type, showing which fields can be imported and their requirements.",
              "type": "text/plain"
            },
            "url": {
              "path": [
                "import",
                "v1",
                "mappings"
              ],
              "host": [
                "{{baseUrl}}"
              ],
              "query": [
                {
                  "disabled": false,
                  "key": "entity_type",
                  "value": "<string>",
                  "description": "Filter by entity type"
                }
              ],
              "variable": []
            },
            "header": [
              {
                "key": "Accept",
                "value": "application/json"
              }
            ],
            "method": "GET",
            "auth": null
          },
          "response": [
            {
              "id": "07e0126f-0e7f-4159-b858-64364443ec69",
              "name": "Field mapping information",
              "originalRequest": {
                "url": {
                  "path": [
                    "import",
                    "v1",
                    "mappings"
                  ],
                  "host": [
                    "{{baseUrl}}"
                  ],
                  "query": [
                    {
                      "key": "entity_type",
                      "value": "<string>"
                    }
                  ],
                  "variable": []
                },
                "header": [
                  {
                    "description": {
                      "content": "Added as a part of security scheme: bearer",
                      "type": "text/plain"
                    },
                    "key": "Authorization",
                    "value": "Bearer <token>"
                  },
                  {
                    "key": "Accept",
                    "value": "application/json"
                  }
                ],
                "method": "GET",
                "body": {}
              },
              "status": "OK",
              "code": 200,
              "header": [
                {
                  "key": "Content-Type",
                  "value": "application/json"
                }
              ],
              "body": "{\n  \"mappings\": [\n    {\n      \"entity_type\": \"string\",\n      \"field_name\": \"string\",\n      \"field_type\": \"string\",\n      \"required\": false,\n      \"description\": \"string\"\n    },\n    {\n      \"entity_type\": \"string\",\n      \"field_name\": \"string\",\n      \"field_type\": \"string\",\n      \"required\": false,\n      \"description\": \"string\"\n    }\n  ]\n}",
              "cookie": [],
              "_postman_previewlanguage": "json"
            },
            {
              "id": "720a9776-3828-433d-93e0-683602a10b34",
              "name": "Unauthorized",
              "originalRequest": {
                "url": {
                  "path": [
                    "import",
                    "v1",
                    "mappings"
                  ],
                  "host": [
                    "{{baseUrl}}"
                  ],
                  "query": [
                    {
                      "key": "entity_type",
                      "value": "<string>"
                    }
                  ],
                  "variable": []
                },
                "header": [
                  {
                    "description": {
                      "content": "Added as a part of security scheme: bearer",
                      "type": "text/plain"
                    },
                    "key": "Authorization",
                    "value": "Bearer <token>"
                  }
                ],
                "method": "GET",
                "body": {}
              },
              "status": "Unauthorized",
              "code": 401,
              "header": [
                {
                  "key": "Content-Type",
                  "value": "text/plain"
                }
              ],
              "body": "",
              "cookie": [],
              "_postman_previewlanguage": "text"
            }
          ],
          "event": [],
          "protocolProfileBehavior": {
            "disableBodyPruning": true
          }
        }
      ],
      "event": []
    },
    {
      "id": "b7179d69-4516-45fc-8d87-e61e6c15f3a3",
      "name": "Uploads",
      "description": {
        "content": "Upload data files for import",
        "type": "text/plain"
      },
      "item": [
        {
          "id": "166804f9-ec27-4f5d-b565-171522275953",
          "name": "Demandbase Upload import file",
          "request": {
            "name": "Demandbase Upload import file",
            "description": {
              "content": "Upload a CSV file for an import job. The file must match the field mappings specified when creating the job.",
              "type": "text/plain"
            },
            "url": {
              "path": [
                "import",
                "v1",
                "jobs",
                ":jobId",
                "upload"
              ],
              "host": [
                "{{baseUrl}}"
              ],
              "query": [],
              "variable": [
                {
                  "disabled": false,
                  "type": "any",
                  "value": "<string>",
                  "key": "jobId",
                  "description": "(Required) Import job unique identifier"
                }
              ]
            },
            "header": [
              {
                "key": "Content-Type",
                "value": "multipart/form-data"
              },
              {
                "key": "Accept",
                "value": "application/json"
              }
            ],
            "method": "POST",
            "auth": null,
            "body": {
              "mode": "formdata",
              "formdata": [
                {
                  "key": "file",
                  "type": "file",
                  "description": "(Required) CSV file to import"
                }
              ]
            }
          },
          "response": [
            {
              "id": "0372c3a2-6ad7-4d14-a379-939dff0454d8",
              "name": "File uploaded and validation started",
              "originalRequest": {
                "url": {
                  "path": [
                    "import",
                    "v1",
                    "jobs",
                    ":jobId",
                    "upload"
                  ],
                  "host": [
                    "{{baseUrl}}"
                  ],
                  "query": [],
                  "variable": [
                    {
                      "disabled": false,
                      "type": "any",
                      "value": "<string>",
                      "key": "jobId",
                      "description": "(Required) Import job unique identifier"
                    }
                  ]
                },
                "header": [
                  {
                    "description": {
                      "content": "Added as a part of security scheme: bearer",
                      "type": "text/plain"
                    },
                    "key": "Authorization",
                    "value": "Bearer <token>"
                  },
                  {
                    "key": "Accept",
                    "value": "application/json"
                  }
                ],
                "method": "POST",
                "body": {
                  "mode": "formdata",
                  "formdata": [
                    {
                      "description": {
                        "content": "(Required) CSV file to import",
                        "type": "text/plain"
                      },
                      "key": "file",
                      "value": "<binary>",
                      "type": "text"
                    }
                  ]
                }
              },
              "status": "OK",
              "code": 200,
              "header": [
                {
                  "key": "Content-Type",
                  "value": "application/json"
                }
              ],
              "body": "{\n  \"id\": \"string\",\n  \"entity_type\": \"people\",\n  \"operation\": \"upsert\",\n  \"status\": \"failed\",\n  \"total_rows\": 1407,\n  \"processed_rows\": 8801,\n  \"success_count\": 2038,\n  \"error_count\": 7944,\n  \"file_name\": \"string\",\n  \"file_size_bytes\": 2317,\n  \"created_at\": \"1962-04-02T00:35:19.543Z\",\n  \"started_at\": \"1958-12-01T04:03:40.061Z\",\n  \"completed_at\": \"1960-02-06T06:03:52.607Z\",\n  \"error_message\": \"string\"\n}",
              "cookie": [],
              "_postman_previewlanguage": "json"
            },
            {
              "id": "2bd8f8d0-a39f-45bf-9ab5-1eafe9127283",
              "name": "Invalid file format or content",
              "originalRequest": {
                "url": {
                  "path": [
                    "import",
                    "v1",
                    "jobs",
                    ":jobId",
                    "upload"
                  ],
                  "host": [
                    "{{baseUrl}}"
                  ],
                  "query": [],
                  "variable": [
                    {
                      "disabled": false,
                      "type": "any",
                      "value": "<string>",
                      "key": "jobId",
                      "description": "(Required) Import job unique identifier"
                    }
                  ]
                },
                "header": [
                  {
                    "description": {
                      "content": "Added as a part of security scheme: bearer",
                      "type": "text/plain"
                    },
                    "key": "Authorization",
                    "value": "Bearer <token>"
                  }
                ],
                "method": "POST",
                "body": {
                  "mode": "formdata",
                  "formdata": [
                    {
                      "description": {
                        "content": "(Required) CSV file to import",
                        "type": "text/plain"
                      },
                      "key": "file",
                      "value": "<binary>",
                      "type": "text"
                    }
                  ]
                }
              },
              "status": "Bad Request",
              "code": 400,
              "header": [
                {
                  "key": "Content-Type",
                  "value": "text/plain"
                }
              ],
              "body": "",
              "cookie": [],
              "_postman_previewlanguage": "text"
            },
            {
              "id": "ceeacfad-d5a5-4598-82f7-d5b9a98e8478",
              "name": "Unauthorized",
              "originalRequest": {
                "url": {
                  "path": [
                    "import",
                    "v1",
                    "jobs",
                    ":jobId",
                    "upload"
                  ],
                  "host": [
                    "{{baseUrl}}"
                  ],
                  "query": [],
                  "variable": [
                    {
                      "disabled": false,
                      "type": "any",
                      "value": "<string>",
                      "key": "jobId",
                      "description": "(Required) Import job unique identifier"
                    }
                  ]
                },
                "header": [
                  {
                    "description": {
                      "content": "Added as a part of security scheme: bearer",
                      "type": "text/plain"
                    },
                    "key": "Authorization",
                    "value": "Bearer <token>"
                  }
                ],
                "method": "POST",
                "body": {
                  "mode": "formdata",
                  "formdata": [
                    {
                      "description": {
                        "content": "(Required) CSV file to import",
                        "type": "text/plain"
                      },
                      "key": "file",
                      "value": "<binary>",
                      "type": "text"
                    }
                  ]
                }
              },
              "status": "Unauthorized",
              "code": 401,
              "header": [
                {
                  "key": "Content-Type",
                  "value": "text/plain"
                }
              ],
              "body": "",
              "cookie": [],
              "_postman_previewlanguage": "text"
            },
            {
              "id": "3c2ee4c4-4e86-476f-9092-0c8b38d07915",
              "name": "Import job not found",
              "originalRequest": {
                "url": {
                  "path": [
                    "import",
                    "v1",
                    "jobs",
                    ":jobId",
                    "upload"
                  ],
                  "host": [
                    "{{baseUrl}}"
                  ],
                  "query": [],
                  "variable": [
                    {
                      "disabled": false,
                      "type": "any",
                      "value": "<string>",
                      "key": "jobId",
                      "description": "(Required) Import job unique identifier"
                    }
                  ]
                },
                "header": [
                  {
                    "description": {
                      "content": "Added as a part of security scheme: bearer",
                      "type": "text/plain"
                    },
                    "key": "Authorization",
                    "value": "Bearer <token>"
                  }
                ],
                "method": "POST",
                "body": {
                  "mode": "formdata",
                  "formdata": [
                    {
                      "description": {
                        "content": "(Required) CSV file to import",
                        "type": "text/plain"
                      },
                      "key": "file",
                      "value": "<binary>",
                      "type": "text"
                    }
                  ]
                }
              },
              "status": "Not Found",
              "code": 404,
              "header": [
                {
                  "key": "Content-Type",
                  "value": "text/plain"
                }
              ],
              "body": "",
              "cookie": [],
              "_postman_previewlanguage": "text"
            },
            {
              "id": "1e86014d-8ff9-436c-9feb-627a0e8fd50b",
              "name": "File too large",
              "originalRequest": {
                "url": {
                  "path": [
                    "import",
                    "v1",
                    "jobs",
                    ":jobId",
                    "upload"
                  ],
                  "host": [
                    "{{baseUrl}}"
                  ],
                  "query": [],
                  "variable": [
                    {
                      "disabled": false,
                      "type": "any",
                      "value": "<string>",
                      "key": "jobId",
                      "description": "(Required) Import job unique identifier"
                    }
                  ]
                },
                "header": [
                  {
                    "description": {
                      "content": "Added as a part of security scheme: bearer",
                      "type": "text/plain"
                    },
                    "key": "Authorization",
                    "value": "Bearer <token>"
                  }
                ],
                "method": "POST",
                "body": {
                  "mode": "formdata",
                  "formdata": [
                    {
                      "description": {
                        "content": "(Required) CSV file to import",
                        "type": "text/plain"
                      },
                      "key": "file",
                      "value": "<binary>",
                      "type": "text"
                    }
                  ]
                }
              },
              "status": "Request Entity Too Large",
              "code": 413,
              "header": [
                {
                  "key": "Content-Type",
                  "value": "text/plain"
                }
              ],
              "body": "",
              "cookie": [],
              "_postman_previewlanguage": "text"
            }
          ],
          "event": [],
          "protocolProfileBehavior": {
            "disableBodyPruning": true
          }
        }
      ],
      "event": []
    }
  ],
  "event": [],
  "variable": [
    {
      "type": "string",
      "value": "https://api.demandbase.com",
      "key": "baseUrl"
    }
  ],
  "auth": {
    "type": "bearer",
    "bearer": [
      {
        "key": "token",
        "value": "{{bearerToken}}"
      }
    ]
  },
  "info": {
    "_postman_id": "a118e270-408c-4b60-9c10-47b75a00e521",
    "name": "Demandbase Data Import API",
    "schema": "https://schema.getpostman.com/json/collection/v2.1.0/collection.json",
    "description": {
      "content": "Allows bulk, asynchronous, programmatic import of new data rows into Demandbase One or updates to existing records, supporting data on accounts, people, opportunities, and activities with CSV-based ingestion.\n\nContact Support:\n Name: Demandbase Support",
      "type": "text/plain"
    }
  }
}